stylizedprint/__init__.py
stylizedprint/animations.py
stylizedprint/borders.py
stylizedprint/colors.py
stylizedprint/core.py
stylizedprint/formatting.py
stylizedprint/prueba.py
stylizedprint/separator.py
stylizedprint/styles.py
stylizedprint/themes.py
stylizedprint/themes_func.py
stylizedprint/utils.py
stylizedprint-0.2.1.dist-info/LICENSE
stylizedprint-0.2.1.dist-info/METADATA
stylizedprint-0.2.1.dist-info/WHEEL
stylizedprint-0.2.1.dist-info/top_level.txt
stylizedprint-0.2.1.dist-info/RECORD
