Metadata-Version: 2.1
Name: stylizedprint
Version: 0.2.1
Summary: A package for creating stylish console prints with ease
Home-page: https://github.com/unaizubeldia/stylizedprint
Author: Unai Zubeldia, Ruben Jordana, Peio Garcia
Maintainer: Unai Zubeldia, Ruben Jordana, Peio Garcia
Maintainer-email: unai.zubeldia@alumni.mondragon.edu, ruben.jordana@alumni.mondragon.edu, peio.garcia@alumni.mondragon.edu
Classifier: Programming Language :: Python :: 3
Classifier: License :: OSI Approved :: MIT License
Classifier: Operating System :: OS Independent
Requires-Python: >=3.6
License-File: LICENSE
Requires-Dist: colorama
Requires-Dist: rich
